steerex/__init__.py
steerex/analysis/__init__.py
steerex/analysis/similarity.py
steerex/analysis/visualization.py
steerex/backends/__init__.py
steerex/backends/base.py
steerex/backends/huggingface.py
steerex/backends/transformerlens.py
steerex/core/__init__.py
steerex/core/config.py
steerex/core/datapoint.py
steerex/core/result.py
steerex/core/types.py
steerex/evaluation/__init__.py
steerex/evaluation/generation.py
steerex/evaluation/probability.py
steerex/extraction/__init__.py
steerex/extraction/base.py
steerex/extraction/caa.py
steerex/extraction/datapoint.py
steerex/extraction/factory.py
steerex/extraction/gradient.py
steerex/optimization/__init__.py
steerex/optimization/callbacks.py
steerex/optimization/loss.py
steerex/optimization/optimizer.py
steerex/steering/__init__.py
steerex/steering/affine.py
steerex/steering/base.py
steerex/steering/clamp.py
steerex/steering/vector.py
steerex/storage/__init__.py
steerex/storage/models.py
steerex/storage/repository.py
steerex-0.1.0.dist-info/METADATA
steerex-0.1.0.dist-info/WHEEL
steerex-0.1.0.dist-info/RECORD
