Metadata-Version: 2.4
Name: steerex
Version: 0.1.0
Summary: A research platform for LLM steering vector optimization and analysis
Project-URL: Homepage, https://github.com/AyseAsude/steerex
Project-URL: Documentation, https://github.com/AyseAsude/steerex#readme
Project-URL: Repository, https://github.com/AyseAsude/steerex
License-Expression: MIT
Keywords: activation engineering,alignment,interpretability,llm,steering
Classifier: Development Status :: 3 - Alpha
Classifier: Intended Audience :: Science/Research
Classifier: License :: OSI Approved :: MIT License
Classifier: Programming Language :: Python :: 3
Classifier: Programming Language :: Python :: 3.10
Classifier: Programming Language :: Python :: 3.11
Classifier: Programming Language :: Python :: 3.12
Classifier: Topic :: Scientific/Engineering :: Artificial Intelligence
Requires-Python: >=3.10
Requires-Dist: matplotlib>=3.10.8
Requires-Dist: numpy>=1.24.0
Requires-Dist: pydantic>=2.0.0
Requires-Dist: python-dotenv>=1.0.0
Requires-Dist: scikit-learn>=1.7.2
Requires-Dist: transformers>=4.30.0
Provides-Extra: all
Requires-Dist: matplotlib>=3.7.0; extra == 'all'
Requires-Dist: mypy>=1.0.0; extra == 'all'
Requires-Dist: plotly>=5.15.0; extra == 'all'
Requires-Dist: pytest-cov>=4.0.0; extra == 'all'
Requires-Dist: pytest>=7.0.0; extra == 'all'
Requires-Dist: ruff>=0.1.0; extra == 'all'
Requires-Dist: scikit-learn>=1.3.0; extra == 'all'
Requires-Dist: umap-learn>=0.5.0; extra == 'all'
Provides-Extra: analysis
Requires-Dist: matplotlib>=3.7.0; extra == 'analysis'
Requires-Dist: plotly>=5.15.0; extra == 'analysis'
Requires-Dist: scikit-learn>=1.3.0; extra == 'analysis'
Requires-Dist: umap-learn>=0.5.0; extra == 'analysis'
Provides-Extra: dev
Requires-Dist: mypy>=1.0.0; extra == 'dev'
Requires-Dist: pytest-cov>=4.0.0; extra == 'dev'
Requires-Dist: pytest>=7.0.0; extra == 'dev'
Requires-Dist: ruff>=0.1.0; extra == 'dev'
